{
  "formatVersion": 1,
  "database": {
    "version": 3,
    "identityHash": "b5886c655d85c8e411730a4591fca58b",
    "entities": [
      {
        "tableName": "tags",
        "createSql": "CREATE TABLE IF NOT EXISTS `${TABLE_NAME}` (`id` INTEGER PRIMARY KEY AUTOINCREMENT NOT NULL, `parentId` INTEGER, `name` TEXT NOT NULL, `sortOrder` INTEGER NOT NULL, `isExpanded` INTEGER NOT NULL, `imageCount` INTEGER NOT NULL)",
        "fields": [
          {
            "fieldPath": "id",
            "columnName": "id",
            "affinity": "INTEGER",
            "notNull": true
          },
          {
            "fieldPath": "parentId",
            "columnName": "parentId",
            "affinity": "INTEGER",
            "notNull": false
          },
          {
            "fieldPath": "name",
            "columnName": "name",
            "affinity": "TEXT",
            "notNull": true
          },
          {
            "fieldPath": "sortOrder",
            "columnName": "sortOrder",
            "affinity": "INTEGER",
            "notNull": true
          },
          {
            "fieldPath": "isExpanded",
            "columnName": "isExpanded",
            "affinity": "INTEGER",
            "notNull": true
          },
          {
            "fieldPath": "imageCount",
            "columnName": "imageCount",
            "affinity": "INTEGER",
            "notNull": true
          }
        ],
        "primaryKey": {
          "autoGenerate": true,
          "columnNames": [
            "id"
          ]
        },
        "indices": [],
        "foreignKeys": []
      },
      {
        "tableName": "media_tag_cross_ref",
        "createSql": "CREATE TABLE IF NOT EXISTS `${TABLE_NAME}` (`mediaPath` TEXT NOT NULL, `tagId` INTEGER NOT NULL, PRIMARY KEY(`mediaPath`, `tagId`))",
        "fields": [
          {
            "fieldPath": "mediaPath",
            "columnName": "mediaPath",
            "affinity": "TEXT",
            "notNull": true
          },
          {
            "fieldPath": "tagId",
            "columnName": "tagId",
            "affinity": "INTEGER",
            "notNull": true
          }
        ],
        "primaryKey": {
          "autoGenerate": false,
          "columnNames": [
            "mediaPath",
            "tagId"
          ]
        },
        "indices": [
          {
            "name": "index_media_tag_cross_ref_tagId",
            "unique": false,
            "columnNames": [
              "tagId"
            ],
            "orders": [],
            "createSql": "CREATE INDEX IF NOT EXISTS `index_media_tag_cross_ref_tagId` ON `${TABLE_NAME}` (`tagId`)"
          }
        ],
        "foreignKeys": []
      },
      {
        "tableName": "tag_references",
        "createSql": "CREATE TABLE IF NOT EXISTS `${TABLE_NAME}` (`parentTagId` INTEGER NOT NULL, `childTagId` INTEGER NOT NULL, `sortOrder` INTEGER NOT NULL, PRIMARY KEY(`parentTagId`, `childTagId`))",
        "fields": [
          {
            "fieldPath": "parentTagId",
            "columnName": "parentTagId",
            "affinity": "INTEGER",
            "notNull": true
          },
          {
            "fieldPath": "childTagId",
            "columnName": "childTagId",
            "affinity": "INTEGER",
            "notNull": true
          },
          {
            "fieldPath": "sortOrder",
            "columnName": "sortOrder",
            "affinity": "INTEGER",
            "notNull": true
          }
        ],
        "primaryKey": {
          "autoGenerate": false,
          "columnNames": [
            "parentTagId",
            "childTagId"
          ]
        },
        "indices": [
          {
            "name": "index_tag_references_childTagId",
            "unique": false,
            "columnNames": [
              "childTagId"
            ],
            "orders": [],
            "createSql": "CREATE INDEX IF NOT EXISTS `index_tag_references_childTagId` ON `${TABLE_NAME}` (`childTagId`)"
          }
        ],
        "foreignKeys": []
      }
    ],
    "views": [],
    "setupQueries": [
      "CREATE TABLE IF NOT EXISTS room_master_table (id INTEGER PRIMARY KEY,identity_hash TEXT)",
      "INSERT OR REPLACE INTO room_master_table (id,identity_hash) VALUES(42, 'b5886c655d85c8e411730a4591fca58b')"
    ]
  }
}